fabulist/__init__.py
fabulist/fabulist.py
fabulist/lorem_ipsum.py
fabulist/data/adj_list.txt
fabulist/data/adv_list.txt
fabulist/data/firstname_list.txt
fabulist/data/lastname_list.txt
fabulist/data/lorem_faust.txt
fabulist/data/lorem_ipsum.txt
fabulist/data/lorem_kafka.txt
fabulist/data/lorem_pulp.txt
fabulist/data/lorem_romeo.txt
fabulist/data/lorem_tao.txt
fabulist/data/lorem_trappatoni.txt
fabulist/data/lorem_werther.txt
fabulist/data/noun_list.txt
fabulist/data/noun_list_animals.txt
fabulist/data/noun_list_computer.txt
fabulist/data/verb_list.txt
fabulist-2.0.1.data/data/CHANGELOG.md
fabulist-2.0.1.dist-info/LICENSE.txt
fabulist-2.0.1.dist-info/METADATA
fabulist-2.0.1.dist-info/WHEEL
fabulist-2.0.1.dist-info/top_level.txt
fabulist-2.0.1.dist-info/RECORD
