Metadata-Version: 2.1
Name: fabulist
Version: 2.0.1
Summary: "Generate random strings that make sense."
Home-page: https://github.com/mar10/fabulist/
Author: Martin Wendt
Author-email: fabulist@wwwendt.de
Maintainer: Martin Wendt
Maintainer-email: fabulist@wwwendt.de
License: MIT
Project-URL: Bug Tracker, https://github.com/mar10/fabulist/issues
Project-URL: Source Code, https://github.com/mar10/fabulist
Project-URL: Documentation, https://fabulist.readthedocs.io/
Project-URL: Download, https://github.com/mar10/fabulist/releases/latest
Keywords: python test-data word-list generator mock
Classifier: Development Status :: 4 - Beta
Classifier: Intended Audience :: Developers
Classifier: License :: OSI Approved :: MIT License
Classifier: Operating System :: OS Independent
Classifier: Programming Language :: Python
Classifier: Programming Language :: Python :: 3
Classifier: Programming Language :: Python :: 3 :: Only
Classifier: Programming Language :: Python :: 3.9
Classifier: Programming Language :: Python :: 3.10
Classifier: Programming Language :: Python :: 3.11
Classifier: Programming Language :: Python :: 3.12
Classifier: Topic :: Software Development :: Libraries :: Python Modules
License-File: LICENSE.txt
